giturlparse/__init__.py
giturlparse/parser.py
git_url_parse-1.2.1.dist-info/AUTHORS.rst
git_url_parse-1.2.1.dist-info/LICENSE
git_url_parse-1.2.1.dist-info/METADATA
git_url_parse-1.2.1.dist-info/WHEEL
git_url_parse-1.2.1.dist-info/pbr.json
git_url_parse-1.2.1.dist-info/top_level.txt
git_url_parse-1.2.1.dist-info/RECORD
